[{"name":"abstract class HikagePreview(context: Context, attrs: AttributeSet? = null) : FrameLayout, HikageBuilder","description":"com.highcapable.hikage.core.preview.HikagePreview","location":"hikage-core/com.highcapable.hikage.core.preview/-hikage-preview/index.html","searchKeys":["HikagePreview","abstract class HikagePreview(context: Context, attrs: AttributeSet? = null) : FrameLayout, HikageBuilder","com.highcapable.hikage.core.preview.HikagePreview"]},{"name":"abstract fun actualViewId(id: String): Int","description":"com.highcapable.hikage.core.Hikage.Performer.actualViewId","location":"hikage-core/com.highcapable.hikage.core/-hikage/-performer/actual-view-id.html","searchKeys":["actualViewId","abstract fun actualViewId(id: String): Int","com.highcapable.hikage.core.Hikage.Performer.actualViewId"]},{"name":"abstract fun bitmapResource(resId: Int): Bitmap","description":"com.highcapable.hikage.core.layout.extension.ResourcesScope.bitmapResource","location":"hikage-core/com.highcapable.hikage.core.layout.extension/-resources-scope/bitmap-resource.html","searchKeys":["bitmapResource","abstract fun bitmapResource(resId: Int): Bitmap","com.highcapable.hikage.core.layout.extension.ResourcesScope.bitmapResource"]},{"name":"abstract fun booleanResource(resId: Int): Boolean","description":"com.highcapable.hikage.core.layout.extension.ResourcesScope.booleanResource","location":"hikage-core/com.highcapable.hikage.core.layout.extension/-resources-scope/boolean-resource.html","searchKeys":["booleanResource","abstract fun booleanResource(resId: Int): Boolean","com.highcapable.hikage.core.layout.extension.ResourcesScope.booleanResource"]},{"name":"abstract fun build(): Hikage.Delegate<*>","description":"com.highcapable.hikage.core.builder.HikageBuilder.build","location":"hikage-core/com.highcapable.hikage.core.builder/-hikage-builder/build.html","searchKeys":["build","abstract fun build(): Hikage.Delegate<*>","com.highcapable.hikage.core.builder.HikageBuilder.build"]},{"name":"abstract fun colorResource(resId: Int): Int","description":"com.highcapable.hikage.core.layout.extension.ResourcesScope.colorResource","location":"hikage-core/com.highcapable.hikage.core.layout.extension/-resources-scope/color-resource.html","searchKeys":["colorResource","abstract fun colorResource(resId: Int): Int","com.highcapable.hikage.core.layout.extension.ResourcesScope.colorResource"]},{"name":"abstract fun createView(parent: ViewGroup?, base: View?, context: Context, params: HikageFactory.Params): View?","description":"com.highcapable.hikage.core.base.HikageFactory.createView","location":"hikage-core/com.highcapable.hikage.core.base/-hikage-factory/create-view.html","searchKeys":["createView","abstract fun createView(parent: ViewGroup?, base: View?, context: Context, params: HikageFactory.Params): View?","com.highcapable.hikage.core.base.HikageFactory.createView"]},{"name":"abstract fun dimenPixelOffsetResource(resId: Int): Int","description":"com.highcapable.hikage.core.layout.extension.ResourcesScope.dimenPixelOffsetResource","location":"hikage-core/com.highcapable.hikage.core.layout.extension/-resources-scope/dimen-pixel-offset-resource.html","searchKeys":["dimenPixelOffsetResource","abstract fun dimenPixelOffsetResource(resId: Int): Int","com.highcapable.hikage.core.layout.extension.ResourcesScope.dimenPixelOffsetResource"]},{"name":"abstract fun dimenPixelSizeResource(resId: Int): Int","description":"com.highcapable.hikage.core.layout.extension.ResourcesScope.dimenPixelSizeResource","location":"hikage-core/com.highcapable.hikage.core.layout.extension/-resources-scope/dimen-pixel-size-resource.html","searchKeys":["dimenPixelSizeResource","abstract fun dimenPixelSizeResource(resId: Int): Int","com.highcapable.hikage.core.layout.extension.ResourcesScope.dimenPixelSizeResource"]},{"name":"abstract fun dimenResource(resId: Int): Float","description":"com.highcapable.hikage.core.layout.extension.ResourcesScope.dimenResource","location":"hikage-core/com.highcapable.hikage.core.layout.extension/-resources-scope/dimen-resource.html","searchKeys":["dimenResource","abstract fun dimenResource(resId: Int): Float","com.highcapable.hikage.core.layout.extension.ResourcesScope.dimenResource"]},{"name":"abstract fun drawableResource(resId: Int): Drawable","description":"com.highcapable.hikage.core.layout.extension.ResourcesScope.drawableResource","location":"hikage-core/com.highcapable.hikage.core.layout.extension/-resources-scope/drawable-resource.html","searchKeys":["drawableResource","abstract fun drawableResource(resId: Int): Drawable","com.highcapable.hikage.core.layout.extension.ResourcesScope.drawableResource"]},{"name":"abstract fun fontResource(resId: Int): Typeface?","description":"com.highcapable.hikage.core.layout.extension.ResourcesScope.fontResource","location":"hikage-core/com.highcapable.hikage.core.layout.extension/-resources-scope/font-resource.html","searchKeys":["fontResource","abstract fun fontResource(resId: Int): Typeface?","com.highcapable.hikage.core.layout.extension.ResourcesScope.fontResource"]},{"name":"abstract fun fractionResource(resId: Int, base: Int, pbase: Int): Float","description":"com.highcapable.hikage.core.layout.extension.ResourcesScope.fractionResource","location":"hikage-core/com.highcapable.hikage.core.layout.extension/-resources-scope/fraction-resource.html","searchKeys":["fractionResource","abstract fun fractionResource(resId: Int, base: Int, pbase: Int): Float","com.highcapable.hikage.core.layout.extension.ResourcesScope.fractionResource"]},{"name":"abstract fun integerArrayResource(resId: Int): IntArray","description":"com.highcapable.hikage.core.layout.extension.ResourcesScope.integerArrayResource","location":"hikage-core/com.highcapable.hikage.core.layout.extension/-resources-scope/integer-array-resource.html","searchKeys":["integerArrayResource","abstract fun integerArrayResource(resId: Int): IntArray","com.highcapable.hikage.core.layout.extension.ResourcesScope.integerArrayResource"]},{"name":"abstract fun integerResource(resId: Int): Int","description":"com.highcapable.hikage.core.layout.extension.ResourcesScope.integerResource","location":"hikage-core/com.highcapable.hikage.core.layout.extension/-resources-scope/integer-resource.html","searchKeys":["integerResource","abstract fun integerResource(resId: Int): Int","com.highcapable.hikage.core.layout.extension.ResourcesScope.integerResource"]},{"name":"abstract fun pluralStringResource(resId: Int, quantity: Int, vararg formatArgs: Any): String","description":"com.highcapable.hikage.core.layout.extension.ResourcesScope.pluralStringResource","location":"hikage-core/com.highcapable.hikage.core.layout.extension/-resources-scope/plural-string-resource.html","searchKeys":["pluralStringResource","abstract fun pluralStringResource(resId: Int, quantity: Int, vararg formatArgs: Any): String","com.highcapable.hikage.core.layout.extension.ResourcesScope.pluralStringResource"]},{"name":"abstract fun pluralTextResource(resId: Int, quantity: Int): CharSequence","description":"com.highcapable.hikage.core.layout.extension.ResourcesScope.pluralTextResource","location":"hikage-core/com.highcapable.hikage.core.layout.extension/-resources-scope/plural-text-resource.html","searchKeys":["pluralTextResource","abstract fun pluralTextResource(resId: Int, quantity: Int): CharSequence","com.highcapable.hikage.core.layout.extension.ResourcesScope.pluralTextResource"]},{"name":"abstract fun set(name: String, value: Boolean)","description":"com.highcapable.hikage.core.attribute.AttributeScope.set","location":"hikage-core/com.highcapable.hikage.core.attribute/-attribute-scope/set.html","searchKeys":["set","abstract fun set(name: String, value: Boolean)","com.highcapable.hikage.core.attribute.AttributeScope.set"]},{"name":"abstract fun set(name: String, value: Float)","description":"com.highcapable.hikage.core.attribute.AttributeScope.set","location":"hikage-core/com.highcapable.hikage.core.attribute/-attribute-scope/set.html","searchKeys":["set","abstract fun set(name: String, value: Float)","com.highcapable.hikage.core.attribute.AttributeScope.set"]},{"name":"abstract fun set(name: String, value: Int)","description":"com.highcapable.hikage.core.attribute.AttributeScope.set","location":"hikage-core/com.highcapable.hikage.core.attribute/-attribute-scope/set.html","searchKeys":["set","abstract fun set(name: String, value: Int)","com.highcapable.hikage.core.attribute.AttributeScope.set"]},{"name":"abstract fun set(name: String, value: String)","description":"com.highcapable.hikage.core.attribute.AttributeScope.set","location":"hikage-core/com.highcapable.hikage.core.attribute/-attribute-scope/set.html","searchKeys":["set","abstract fun set(name: String, value: String)","com.highcapable.hikage.core.attribute.AttributeScope.set"]},{"name":"abstract fun stateColorResource(resId: Int): ColorStateList","description":"com.highcapable.hikage.core.layout.extension.ResourcesScope.stateColorResource","location":"hikage-core/com.highcapable.hikage.core.layout.extension/-resources-scope/state-color-resource.html","searchKeys":["stateColorResource","abstract fun stateColorResource(resId: Int): ColorStateList","com.highcapable.hikage.core.layout.extension.ResourcesScope.stateColorResource"]},{"name":"abstract fun stringArrayResource(resId: Int): Array<String>","description":"com.highcapable.hikage.core.layout.extension.ResourcesScope.stringArrayResource","location":"hikage-core/com.highcapable.hikage.core.layout.extension/-resources-scope/string-array-resource.html","searchKeys":["stringArrayResource","abstract fun stringArrayResource(resId: Int): Array<String>","com.highcapable.hikage.core.layout.extension.ResourcesScope.stringArrayResource"]},{"name":"abstract fun stringResource(resId: Int, vararg formatArgs: Any): String","description":"com.highcapable.hikage.core.layout.extension.ResourcesScope.stringResource","location":"hikage-core/com.highcapable.hikage.core.layout.extension/-resources-scope/string-resource.html","searchKeys":["stringResource","abstract fun stringResource(resId: Int, vararg formatArgs: Any): String","com.highcapable.hikage.core.layout.extension.ResourcesScope.stringResource"]},{"name":"abstract fun textResource(resId: Int): CharSequence","description":"com.highcapable.hikage.core.layout.extension.ResourcesScope.textResource","location":"hikage-core/com.highcapable.hikage.core.layout.extension/-resources-scope/text-resource.html","searchKeys":["textResource","abstract fun textResource(resId: Int): CharSequence","com.highcapable.hikage.core.layout.extension.ResourcesScope.textResource"]},{"name":"annotation class Hikagable","description":"com.highcapable.hikage.annotation.Hikagable","location":"hikage-core/com.highcapable.hikage.annotation/-hikagable/index.html","searchKeys":["Hikagable","annotation class Hikagable","com.highcapable.hikage.annotation.Hikagable"]},{"name":"annotation class HikageView(val lparams: KClass<*> = Any::class, val alias: String = \"\", val attrs: Boolean = true, val init: Boolean = true, val performer: Boolean = true)","description":"com.highcapable.hikage.annotation.HikageView","location":"hikage-core/com.highcapable.hikage.annotation/-hikage-view/index.html","searchKeys":["HikageView","annotation class HikageView(val lparams: KClass<*> = Any::class, val alias: String = \"\", val attrs: Boolean = true, val init: Boolean = true, val performer: Boolean = true)","com.highcapable.hikage.annotation.HikageView"]},{"name":"annotation class HikageViewDeclaration(val view: KClass<*>, val lparams: KClass<*> = Any::class, val alias: String = \"\", val attrs: Boolean = true, val init: Boolean = true, val performer: Boolean = true)","description":"com.highcapable.hikage.annotation.HikageViewDeclaration","location":"hikage-core/com.highcapable.hikage.annotation/-hikage-view-declaration/index.html","searchKeys":["HikageViewDeclaration","annotation class HikageViewDeclaration(val view: KClass<*>, val lparams: KClass<*> = Any::class, val alias: String = \"\", val attrs: Boolean = true, val init: Boolean = true, val performer: Boolean = true)","com.highcapable.hikage.annotation.HikageViewDeclaration"]},{"name":"class Delegate<LP : ViewGroup.LayoutParams>","description":"com.highcapable.hikage.core.Hikage.Delegate","location":"hikage-core/com.highcapable.hikage.core/-hikage/-delegate/index.html","searchKeys":["Delegate","class Delegate<LP : ViewGroup.LayoutParams>","com.highcapable.hikage.core.Hikage.Delegate"]},{"name":"class Hikage","description":"com.highcapable.hikage.core.Hikage","location":"hikage-core/com.highcapable.hikage.core/-hikage/index.html","searchKeys":["Hikage","class Hikage","com.highcapable.hikage.core.Hikage"]},{"name":"class HikageFactoryBuilder","description":"com.highcapable.hikage.core.base.HikageFactoryBuilder","location":"hikage-core/com.highcapable.hikage.core.base/-hikage-factory-builder/index.html","searchKeys":["HikageFactoryBuilder","class HikageFactoryBuilder","com.highcapable.hikage.core.base.HikageFactoryBuilder"]},{"name":"class LayoutParams","description":"com.highcapable.hikage.core.layout.LayoutParams","location":"hikage-core/com.highcapable.hikage.core.layout/-layout-params/index.html","searchKeys":["LayoutParams","class LayoutParams","com.highcapable.hikage.core.layout.LayoutParams"]},{"name":"constructor(context: Context, attrs: AttributeSet? = null)","description":"com.highcapable.hikage.core.preview.HikagePreview.HikagePreview","location":"hikage-core/com.highcapable.hikage.core.preview/-hikage-preview/-hikage-preview.html","searchKeys":["HikagePreview","constructor(context: Context, attrs: AttributeSet? = null)","com.highcapable.hikage.core.preview.HikagePreview.HikagePreview"]},{"name":"constructor(privateFactory: Boolean = defaultProcessPrivateFactory, privateFactoryViews: List<String> = defaultPrivateFactoryViews)","description":"com.highcapable.hikage.core.base.HikageFactory.Config.Config","location":"hikage-core/com.highcapable.hikage.core.base/-hikage-factory/-config/-config.html","searchKeys":["Config","constructor(privateFactory: Boolean = defaultProcessPrivateFactory, privateFactoryViews: List<String> = defaultPrivateFactoryViews)","com.highcapable.hikage.core.base.HikageFactory.Config.Config"]},{"name":"context(performer: Hikage.Performer<LP>)operator fun <LP : ViewGroup.LayoutParams> Hikage.Delegate<*>.invoke(lparams: LayoutParams? = null, id: String? = null, embedded: Boolean = true): Hikage","description":"com.highcapable.hikage.core.layout.invoke","location":"hikage-core/com.highcapable.hikage.core.layout/invoke.html","searchKeys":["invoke","context(performer: Hikage.Performer<LP>)operator fun <LP : ViewGroup.LayoutParams> Hikage.Delegate<*>.invoke(lparams: LayoutParams? = null, id: String? = null, embedded: Boolean = true): Hikage","com.highcapable.hikage.core.layout.invoke"]},{"name":"data class Config(val privateFactory: Boolean = defaultProcessPrivateFactory, val privateFactoryViews: List<String> = defaultPrivateFactoryViews)","description":"com.highcapable.hikage.core.base.HikageFactory.Config","location":"hikage-core/com.highcapable.hikage.core.base/-hikage-factory/-config/index.html","searchKeys":["Config","data class Config(val privateFactory: Boolean = defaultProcessPrivateFactory, val privateFactoryViews: List<String> = defaultPrivateFactoryViews)","com.highcapable.hikage.core.base.HikageFactory.Config"]},{"name":"data class Params","description":"com.highcapable.hikage.core.base.HikageFactory.Params","location":"hikage-core/com.highcapable.hikage.core.base/-hikage-factory/-params/index.html","searchKeys":["Params","data class Params","com.highcapable.hikage.core.base.HikageFactory.Params"]},{"name":"fun <LP : ViewGroup.LayoutParams> Hikage.Performer<LP>.Layout(delegate: Hikage.Delegate<*>, lparams: LayoutParams? = null, id: String? = null, embedded: Boolean = true): Hikage","description":"com.highcapable.hikage.core.layout.Layout","location":"hikage-core/com.highcapable.hikage.core.layout/-layout.html","searchKeys":["Layout","fun <LP : ViewGroup.LayoutParams> Hikage.Performer<LP>.Layout(delegate: Hikage.Delegate<*>, lparams: LayoutParams? = null, id: String? = null, embedded: Boolean = true): Hikage","com.highcapable.hikage.core.layout.Layout"]},{"name":"fun <LP : ViewGroup.LayoutParams> Hikage.Performer<LP>.Layout(hikage: Hikage, lparams: LayoutParams? = null, id: String? = null): Hikage","description":"com.highcapable.hikage.core.layout.Layout","location":"hikage-core/com.highcapable.hikage.core.layout/-layout.html","searchKeys":["Layout","fun <LP : ViewGroup.LayoutParams> Hikage.Performer<LP>.Layout(hikage: Hikage, lparams: LayoutParams? = null, id: String? = null): Hikage","com.highcapable.hikage.core.layout.Layout"]},{"name":"fun <LP : ViewGroup.LayoutParams> Hikage.Performer<LP>.Layout(resId: Int, lparams: LayoutParams? = null, id: String? = null): View","description":"com.highcapable.hikage.core.layout.Layout","location":"hikage-core/com.highcapable.hikage.core.layout/-layout.html","searchKeys":["Layout","fun <LP : ViewGroup.LayoutParams> Hikage.Performer<LP>.Layout(resId: Int, lparams: LayoutParams? = null, id: String? = null): View","com.highcapable.hikage.core.layout.Layout"]},{"name":"fun <LP : ViewGroup.LayoutParams> Hikage.Performer<LP>.Layout(view: View, lparams: LayoutParams? = null, id: String? = null): View","description":"com.highcapable.hikage.core.layout.Layout","location":"hikage-core/com.highcapable.hikage.core.layout/-layout.html","searchKeys":["Layout","fun <LP : ViewGroup.LayoutParams> Hikage.Performer<LP>.Layout(view: View, lparams: LayoutParams? = null, id: String? = null): View","com.highcapable.hikage.core.layout.Layout"]},{"name":"fun <LP : ViewGroup.LayoutParams> Hikage.Performer<LP>.LayoutParams(width: Int? = null, height: Int? = null, matchParent: Boolean = false, widthMatchParent: Boolean = false, heightMatchParent: Boolean = false, body: LayoutParamsBody<LP> = {}): LayoutParams","description":"com.highcapable.hikage.core.layout.LayoutParams","location":"hikage-core/com.highcapable.hikage.core.layout/-layout-params.html","searchKeys":["LayoutParams","fun <LP : ViewGroup.LayoutParams> Hikage.Performer<LP>.LayoutParams(width: Int? = null, height: Int? = null, matchParent: Boolean = false, widthMatchParent: Boolean = false, heightMatchParent: Boolean = false, body: LayoutParamsBody<LP> = {}): LayoutParams","com.highcapable.hikage.core.layout.LayoutParams"]},{"name":"fun <LP : ViewGroup.LayoutParams> Hikage.Performer<LP>.View(factory: ViewConstructor<View>? = null, lparams: LayoutParams? = null, id: String? = null, attrs: HikageAttribute = {}, init: HikageView<View> = {}): View","description":"com.highcapable.hikage.core.layout.View","location":"hikage-core/com.highcapable.hikage.core.layout/-view.html","searchKeys":["View","fun <LP : ViewGroup.LayoutParams> Hikage.Performer<LP>.View(factory: ViewConstructor<View>? = null, lparams: LayoutParams? = null, id: String? = null, attrs: HikageAttribute = {}, init: HikageView<View> = {}): View","com.highcapable.hikage.core.layout.View"]},{"name":"fun <LP : ViewGroup.LayoutParams> build(lpClass: KClass<LP>, factory: HikageFactoryBuilder.() -> Unit = {}, performer: HikagePerformer<LP>): Hikage.Delegate<LP>","description":"com.highcapable.hikage.core.Hikage.Companion.build","location":"hikage-core/com.highcapable.hikage.core/-hikage/-companion/build.html","searchKeys":["build","fun <LP : ViewGroup.LayoutParams> build(lpClass: KClass<LP>, factory: HikageFactoryBuilder.() -> Unit = {}, performer: HikagePerformer<LP>): Hikage.Delegate<LP>","com.highcapable.hikage.core.Hikage.Companion.build"]},{"name":"fun <LP : ViewGroup.LayoutParams> create(lpClass: KClass<LP>, context: Context, parent: ViewGroup? = null, attachToParent: Boolean = parent != null, factory: HikageFactoryBuilder.() -> Unit = {}, performer: HikagePerformer<LP>): Hikage","description":"com.highcapable.hikage.core.Hikage.Companion.create","location":"hikage-core/com.highcapable.hikage.core/-hikage/-companion/create.html","searchKeys":["create","fun <LP : ViewGroup.LayoutParams> create(lpClass: KClass<LP>, context: Context, parent: ViewGroup? = null, attachToParent: Boolean = parent != null, factory: HikageFactoryBuilder.() -> Unit = {}, performer: HikagePerformer<LP>): Hikage","com.highcapable.hikage.core.Hikage.Companion.create"]},{"name":"fun <V : View, LP : ViewGroup.LayoutParams> Hikage.Performer<LP>.View(viewClass: KClass<V>, factory: ViewConstructor<V>? = null, lparams: LayoutParams? = null, id: String? = null, attrs: HikageAttribute = {}, init: HikageView<V> = {}): V","description":"com.highcapable.hikage.core.layout.View","location":"hikage-core/com.highcapable.hikage.core.layout/-view.html","searchKeys":["View","fun <V : View, LP : ViewGroup.LayoutParams> Hikage.Performer<LP>.View(viewClass: KClass<V>, factory: ViewConstructor<V>? = null, lparams: LayoutParams? = null, id: String? = null, attrs: HikageAttribute = {}, init: HikageView<V> = {}): V","com.highcapable.hikage.core.layout.View"]},{"name":"fun <VB : ViewBinding, LP : ViewGroup.LayoutParams> Hikage.Performer<LP>.Layout(bindingBuilder: ViewBindingBuilder<VB>, lparams: LayoutParams? = null, id: String? = null): VB","description":"com.highcapable.hikage.core.layout.Layout","location":"hikage-core/com.highcapable.hikage.core.layout/-layout.html","searchKeys":["Layout","fun <VB : ViewBinding, LP : ViewGroup.LayoutParams> Hikage.Performer<LP>.Layout(bindingBuilder: ViewBindingBuilder<VB>, lparams: LayoutParams? = null, id: String? = null): VB","com.highcapable.hikage.core.layout.Layout"]},{"name":"fun <VG : ViewGroup, LP : ViewGroup.LayoutParams> Hikage.Performer<LP>.ViewGroup(viewClass: KClass<VG>, factory: ViewConstructor<VG>? = null, lparams: LayoutParams? = null, id: String? = null, attrs: HikageAttribute = {}, init: HikageView<VG> = {}, performer: HikagePerformer<ViewGroup.LayoutParams> = {}): VG","description":"com.highcapable.hikage.core.layout.ViewGroup","location":"hikage-core/com.highcapable.hikage.core.layout/-view-group.html","searchKeys":["ViewGroup","fun <VG : ViewGroup, LP : ViewGroup.LayoutParams> Hikage.Performer<LP>.ViewGroup(viewClass: KClass<VG>, factory: ViewConstructor<VG>? = null, lparams: LayoutParams? = null, id: String? = null, attrs: HikageAttribute = {}, init: HikageView<VG> = {}, performer: HikagePerformer<ViewGroup.LayoutParams> = {}): VG","com.highcapable.hikage.core.layout.ViewGroup"]},{"name":"fun <VG : ViewGroup, NLP : ViewGroup.LayoutParams, LP : ViewGroup.LayoutParams> Hikage.Performer<LP>.ViewGroup(viewClass: KClass<VG>, childLpClass: KClass<NLP>, factory: ViewConstructor<VG>? = null, lparams: LayoutParams? = null, id: String? = null, attrs: HikageAttribute = {}, init: HikageView<VG> = {}, performer: HikagePerformer<NLP> = {}): VG","description":"com.highcapable.hikage.core.layout.ViewGroup","location":"hikage-core/com.highcapable.hikage.core.layout/-view-group.html","searchKeys":["ViewGroup","fun <VG : ViewGroup, NLP : ViewGroup.LayoutParams, LP : ViewGroup.LayoutParams> Hikage.Performer<LP>.ViewGroup(viewClass: KClass<VG>, childLpClass: KClass<NLP>, factory: ViewConstructor<VG>? = null, lparams: LayoutParams? = null, id: String? = null, attrs: HikageAttribute = {}, init: HikageView<VG> = {}, performer: HikagePerformer<NLP> = {}): VG","com.highcapable.hikage.core.layout.ViewGroup"]},{"name":"fun Collection<AttributeItem>.toHikageAttribute(): HikageAttribute","description":"com.highcapable.hikage.core.attribute.toHikageAttribute","location":"hikage-core/com.highcapable.hikage.core.attribute/to-hikage-attribute.html","searchKeys":["toHikageAttribute","fun Collection<AttributeItem>.toHikageAttribute(): HikageAttribute","com.highcapable.hikage.core.attribute.toHikageAttribute"]},{"name":"fun Context.lazyHikage(builder: HikageBuilder, parent: ViewGroup? = null, attachToParent: Boolean = parent != null): Lazy<Hikage>","description":"com.highcapable.hikage.core.builder.lazyHikage","location":"hikage-core/com.highcapable.hikage.core.builder/lazy-hikage.html","searchKeys":["lazyHikage","fun Context.lazyHikage(builder: HikageBuilder, parent: ViewGroup? = null, attachToParent: Boolean = parent != null): Lazy<Hikage>","com.highcapable.hikage.core.builder.lazyHikage"]},{"name":"fun Context.lazyHikage(parent: ViewGroup? = null, attachToParent: Boolean = parent != null, factory: HikageFactoryBuilder.() -> Unit = {}, performer: HikagePerformer<ViewGroup.LayoutParams>): Lazy<Hikage>","description":"com.highcapable.hikage.core.builder.lazyHikage","location":"hikage-core/com.highcapable.hikage.core.builder/lazy-hikage.html","searchKeys":["lazyHikage","fun Context.lazyHikage(parent: ViewGroup? = null, attachToParent: Boolean = parent != null, factory: HikageFactoryBuilder.() -> Unit = {}, performer: HikagePerformer<ViewGroup.LayoutParams>): Lazy<Hikage>","com.highcapable.hikage.core.builder.lazyHikage"]},{"name":"fun Fragment.lazyHikage(builder: HikageBuilder, parent: ViewGroup? = null, attachToParent: Boolean = parent != null): Lazy<Hikage>","description":"com.highcapable.hikage.core.builder.lazyHikage","location":"hikage-core/com.highcapable.hikage.core.builder/lazy-hikage.html","searchKeys":["lazyHikage","fun Fragment.lazyHikage(builder: HikageBuilder, parent: ViewGroup? = null, attachToParent: Boolean = parent != null): Lazy<Hikage>","com.highcapable.hikage.core.builder.lazyHikage"]},{"name":"fun Fragment.lazyHikage(parent: ViewGroup? = null, attachToParent: Boolean = parent != null, factory: HikageFactoryBuilder.() -> Unit = {}, performer: HikagePerformer<ViewGroup.LayoutParams>): Lazy<Hikage>","description":"com.highcapable.hikage.core.builder.lazyHikage","location":"hikage-core/com.highcapable.hikage.core.builder/lazy-hikage.html","searchKeys":["lazyHikage","fun Fragment.lazyHikage(parent: ViewGroup? = null, attachToParent: Boolean = parent != null, factory: HikageFactoryBuilder.() -> Unit = {}, performer: HikagePerformer<ViewGroup.LayoutParams>): Lazy<Hikage>","com.highcapable.hikage.core.builder.lazyHikage"]},{"name":"fun Hikagable(context: Context, parent: ViewGroup? = null, attachToParent: Boolean = parent != null, factory: HikageFactoryBuilder.() -> Unit = {}, performer: HikagePerformer<ViewGroup.LayoutParams>): Hikage","description":"com.highcapable.hikage.core.base.Hikagable","location":"hikage-core/com.highcapable.hikage.core.base/-hikagable.html","searchKeys":["Hikagable","fun Hikagable(context: Context, parent: ViewGroup? = null, attachToParent: Boolean = parent != null, factory: HikageFactoryBuilder.() -> Unit = {}, performer: HikagePerformer<ViewGroup.LayoutParams>): Hikage","com.highcapable.hikage.core.base.Hikagable"]},{"name":"fun Hikagable(factory: HikageFactoryBuilder.() -> Unit = {}, performer: HikagePerformer<ViewGroup.LayoutParams>): Hikage.Delegate<ViewGroup.LayoutParams>","description":"com.highcapable.hikage.core.base.Hikagable","location":"hikage-core/com.highcapable.hikage.core.base/-hikagable.html","searchKeys":["Hikagable","fun Hikagable(factory: HikageFactoryBuilder.() -> Unit = {}, performer: HikagePerformer<ViewGroup.LayoutParams>): Hikage.Delegate<ViewGroup.LayoutParams>","com.highcapable.hikage.core.base.Hikagable"]},{"name":"fun Hikage.Attribute.namespace(name: String): AttributeScope","description":"com.highcapable.hikage.core.attribute.namespace","location":"hikage-core/com.highcapable.hikage.core.attribute/namespace.html","searchKeys":["namespace","fun Hikage.Attribute.namespace(name: String): AttributeScope","com.highcapable.hikage.core.attribute.namespace"]},{"name":"fun Hikage.Attribute.set(name: String, value: Boolean)","description":"com.highcapable.hikage.core.attribute.set","location":"hikage-core/com.highcapable.hikage.core.attribute/set.html","searchKeys":["set","fun Hikage.Attribute.set(name: String, value: Boolean)","com.highcapable.hikage.core.attribute.set"]},{"name":"fun Hikage.Attribute.set(name: String, value: Float)","description":"com.highcapable.hikage.core.attribute.set","location":"hikage-core/com.highcapable.hikage.core.attribute/set.html","searchKeys":["set","fun Hikage.Attribute.set(name: String, value: Float)","com.highcapable.hikage.core.attribute.set"]},{"name":"fun Hikage.Attribute.set(name: String, value: Int)","description":"com.highcapable.hikage.core.attribute.set","location":"hikage-core/com.highcapable.hikage.core.attribute/set.html","searchKeys":["set","fun Hikage.Attribute.set(name: String, value: Int)","com.highcapable.hikage.core.attribute.set"]},{"name":"fun Hikage.Attribute.set(name: String, value: String)","description":"com.highcapable.hikage.core.attribute.set","location":"hikage-core/com.highcapable.hikage.core.attribute/set.html","searchKeys":["set","fun Hikage.Attribute.set(name: String, value: String)","com.highcapable.hikage.core.attribute.set"]},{"name":"fun HikageAttribute(block: HikageAttribute): HikageAttribute","description":"com.highcapable.hikage.core.attribute.HikageAttribute","location":"hikage-core/com.highcapable.hikage.core.attribute/-hikage-attribute.html","searchKeys":["HikageAttribute","fun HikageAttribute(block: HikageAttribute): HikageAttribute","com.highcapable.hikage.core.attribute.HikageAttribute"]},{"name":"fun HikageAttribute.build(): List<AttributeItem>","description":"com.highcapable.hikage.core.attribute.build","location":"hikage-core/com.highcapable.hikage.core.attribute/build.html","searchKeys":["build","fun HikageAttribute.build(): List<AttributeItem>","com.highcapable.hikage.core.attribute.build"]},{"name":"fun HikageAttribute.isNotEmpty(): Boolean","description":"com.highcapable.hikage.core.attribute.isNotEmpty","location":"hikage-core/com.highcapable.hikage.core.attribute/is-not-empty.html","searchKeys":["isNotEmpty","fun HikageAttribute.isNotEmpty(): Boolean","com.highcapable.hikage.core.attribute.isNotEmpty"]},{"name":"fun HikageFactory(inflater: LayoutInflater, config: HikageFactory.Config = HikageFactory.Config()): HikageFactory","description":"com.highcapable.hikage.core.base.HikageFactory","location":"hikage-core/com.highcapable.hikage.core.base/-hikage-factory.html","searchKeys":["HikageFactory","fun HikageFactory(inflater: LayoutInflater, config: HikageFactory.Config = HikageFactory.Config()): HikageFactory","com.highcapable.hikage.core.base.HikageFactory"]},{"name":"fun add(factory: HikageFactory)","description":"com.highcapable.hikage.core.base.HikageFactoryBuilder.add","location":"hikage-core/com.highcapable.hikage.core.base/-hikage-factory-builder/add.html","searchKeys":["add","fun add(factory: HikageFactory)","com.highcapable.hikage.core.base.HikageFactoryBuilder.add"]},{"name":"fun addAll(factories: List<HikageFactory>)","description":"com.highcapable.hikage.core.base.HikageFactoryBuilder.addAll","location":"hikage-core/com.highcapable.hikage.core.base/-hikage-factory-builder/add-all.html","searchKeys":["addAll","fun addAll(factories: List<HikageFactory>)","com.highcapable.hikage.core.base.HikageFactoryBuilder.addAll"]},{"name":"fun build(factory: HikageFactoryBuilder.() -> Unit = {}, performer: HikagePerformer<ViewGroup.LayoutParams>): Hikage.Delegate<ViewGroup.LayoutParams>","description":"com.highcapable.hikage.core.Hikage.Companion.build","location":"hikage-core/com.highcapable.hikage.core/-hikage/-companion/build.html","searchKeys":["build","fun build(factory: HikageFactoryBuilder.() -> Unit = {}, performer: HikagePerformer<ViewGroup.LayoutParams>): Hikage.Delegate<ViewGroup.LayoutParams>","com.highcapable.hikage.core.Hikage.Companion.build"]},{"name":"fun create(): ViewGroup.LayoutParams","description":"com.highcapable.hikage.core.layout.LayoutParams.create","location":"hikage-core/com.highcapable.hikage.core.layout/-layout-params/create.html","searchKeys":["create","fun create(): ViewGroup.LayoutParams","com.highcapable.hikage.core.layout.LayoutParams.create"]},{"name":"fun create(context: Context, parent: ViewGroup? = null, attachToParent: Boolean = parent != null): Hikage","description":"com.highcapable.hikage.core.Hikage.Delegate.create","location":"hikage-core/com.highcapable.hikage.core/-hikage/-delegate/create.html","searchKeys":["create","fun create(context: Context, parent: ViewGroup? = null, attachToParent: Boolean = parent != null): Hikage","com.highcapable.hikage.core.Hikage.Delegate.create"]},{"name":"fun create(context: Context, parent: ViewGroup? = null, attachToParent: Boolean = parent != null, factory: HikageFactoryBuilder.() -> Unit = {}, performer: HikagePerformer<ViewGroup.LayoutParams>): Hikage","description":"com.highcapable.hikage.core.Hikage.Companion.create","location":"hikage-core/com.highcapable.hikage.core/-hikage/-companion/create.html","searchKeys":["create","fun create(context: Context, parent: ViewGroup? = null, attachToParent: Boolean = parent != null, factory: HikageFactoryBuilder.() -> Unit = {}, performer: HikagePerformer<ViewGroup.LayoutParams>): Hikage","com.highcapable.hikage.core.Hikage.Companion.create"]},{"name":"fun getActualViewId(id: String): Int","description":"com.highcapable.hikage.core.Hikage.getActualViewId","location":"hikage-core/com.highcapable.hikage.core/-hikage/get-actual-view-id.html","searchKeys":["getActualViewId","fun getActualViewId(id: String): Int","com.highcapable.hikage.core.Hikage.getActualViewId"]},{"name":"fun getOrNull(id: String): View?","description":"com.highcapable.hikage.core.Hikage.getOrNull","location":"hikage-core/com.highcapable.hikage.core/-hikage/get-or-null.html","searchKeys":["getOrNull","fun getOrNull(id: String): View?","com.highcapable.hikage.core.Hikage.getOrNull"]},{"name":"fun interface HikageFactory","description":"com.highcapable.hikage.core.base.HikageFactory","location":"hikage-core/com.highcapable.hikage.core.base/-hikage-factory/index.html","searchKeys":["HikageFactory","fun interface HikageFactory","com.highcapable.hikage.core.base.HikageFactory"]},{"name":"inline fun <LP : ViewGroup.LayoutParams> Context.lazyHikage(parent: ViewGroup? = null, attachToParent: Boolean = parent != null, noinline factory: HikageFactoryBuilder.() -> Unit = {}, noinline performer: HikagePerformer<LP>): Lazy<Hikage>","description":"com.highcapable.hikage.core.builder.lazyHikage","location":"hikage-core/com.highcapable.hikage.core.builder/lazy-hikage.html","searchKeys":["lazyHikage","inline fun <LP : ViewGroup.LayoutParams> Context.lazyHikage(parent: ViewGroup? = null, attachToParent: Boolean = parent != null, noinline factory: HikageFactoryBuilder.() -> Unit = {}, noinline performer: HikagePerformer<LP>): Lazy<Hikage>","com.highcapable.hikage.core.builder.lazyHikage"]},{"name":"inline fun <LP : ViewGroup.LayoutParams> Fragment.lazyHikage(parent: ViewGroup? = null, attachToParent: Boolean = parent != null, noinline factory: HikageFactoryBuilder.() -> Unit = {}, noinline performer: HikagePerformer<LP>): Lazy<Hikage>","description":"com.highcapable.hikage.core.builder.lazyHikage","location":"hikage-core/com.highcapable.hikage.core.builder/lazy-hikage.html","searchKeys":["lazyHikage","inline fun <LP : ViewGroup.LayoutParams> Fragment.lazyHikage(parent: ViewGroup? = null, attachToParent: Boolean = parent != null, noinline factory: HikageFactoryBuilder.() -> Unit = {}, noinline performer: HikagePerformer<LP>): Lazy<Hikage>","com.highcapable.hikage.core.builder.lazyHikage"]},{"name":"inline fun <LP : ViewGroup.LayoutParams> Hikagable(context: Context, parent: ViewGroup? = null, attachToParent: Boolean = parent != null, noinline factory: HikageFactoryBuilder.() -> Unit = {}, noinline performer: HikagePerformer<LP>): Hikage","description":"com.highcapable.hikage.core.base.Hikagable","location":"hikage-core/com.highcapable.hikage.core.base/-hikagable.html","searchKeys":["Hikagable","inline fun <LP : ViewGroup.LayoutParams> Hikagable(context: Context, parent: ViewGroup? = null, attachToParent: Boolean = parent != null, noinline factory: HikageFactoryBuilder.() -> Unit = {}, noinline performer: HikagePerformer<LP>): Hikage","com.highcapable.hikage.core.base.Hikagable"]},{"name":"inline fun <LP : ViewGroup.LayoutParams> Hikagable(noinline factory: HikageFactoryBuilder.() -> Unit = {}, noinline performer: HikagePerformer<LP>): Hikage.Delegate<LP>","description":"com.highcapable.hikage.core.base.Hikagable","location":"hikage-core/com.highcapable.hikage.core.base/-hikagable.html","searchKeys":["Hikagable","inline fun <LP : ViewGroup.LayoutParams> Hikagable(noinline factory: HikageFactoryBuilder.() -> Unit = {}, noinline performer: HikagePerformer<LP>): Hikage.Delegate<LP>","com.highcapable.hikage.core.base.Hikagable"]},{"name":"inline fun <LP : ViewGroup.LayoutParams> build(noinline factory: HikageFactoryBuilder.() -> Unit = {}, noinline performer: HikagePerformer<LP>): Hikage.Delegate<LP>","description":"com.highcapable.hikage.core.Hikage.Companion.build","location":"hikage-core/com.highcapable.hikage.core/-hikage/-companion/build.html","searchKeys":["build","inline fun <LP : ViewGroup.LayoutParams> build(noinline factory: HikageFactoryBuilder.() -> Unit = {}, noinline performer: HikagePerformer<LP>): Hikage.Delegate<LP>","com.highcapable.hikage.core.Hikage.Companion.build"]},{"name":"inline fun <LP : ViewGroup.LayoutParams> create(context: Context, parent: ViewGroup? = null, attachToParent: Boolean = parent != null, noinline factory: HikageFactoryBuilder.() -> Unit = {}, noinline performer: HikagePerformer<LP>): Hikage","description":"com.highcapable.hikage.core.Hikage.Companion.create","location":"hikage-core/com.highcapable.hikage.core/-hikage/-companion/create.html","searchKeys":["create","inline fun <LP : ViewGroup.LayoutParams> create(context: Context, parent: ViewGroup? = null, attachToParent: Boolean = parent != null, noinline factory: HikageFactoryBuilder.() -> Unit = {}, noinline performer: HikagePerformer<LP>): Hikage","com.highcapable.hikage.core.Hikage.Companion.create"]},{"name":"inline fun <V : View> Hikage.Performer<*>.View(noinline factory: ViewConstructor<V>? = null, lparams: LayoutParams? = null, id: String? = null, noinline attrs: HikageAttribute = {}, noinline init: HikageView<V> = {}): V","description":"com.highcapable.hikage.core.layout.View","location":"hikage-core/com.highcapable.hikage.core.layout/-view.html","searchKeys":["View","inline fun <V : View> Hikage.Performer<*>.View(noinline factory: ViewConstructor<V>? = null, lparams: LayoutParams? = null, id: String? = null, noinline attrs: HikageAttribute = {}, noinline init: HikageView<V> = {}): V","com.highcapable.hikage.core.layout.View"]},{"name":"inline fun <V : View> root(): V","description":"com.highcapable.hikage.core.Hikage.root","location":"hikage-core/com.highcapable.hikage.core/-hikage/root.html","searchKeys":["root","inline fun <V : View> root(): V","com.highcapable.hikage.core.Hikage.root"]},{"name":"inline fun <VB : ViewBinding> Hikage.Performer<*>.Layout(lparams: LayoutParams? = null, id: String? = null): VB","description":"com.highcapable.hikage.core.layout.Layout","location":"hikage-core/com.highcapable.hikage.core.layout/-layout.html","searchKeys":["Layout","inline fun <VB : ViewBinding> Hikage.Performer<*>.Layout(lparams: LayoutParams? = null, id: String? = null): VB","com.highcapable.hikage.core.layout.Layout"]},{"name":"inline fun <VG : ViewGroup, NLP : ViewGroup.LayoutParams> Hikage.Performer<*>.ViewGroup(noinline factory: ViewConstructor<VG>? = null, lparams: LayoutParams? = null, id: String? = null, noinline attrs: HikageAttribute = {}, noinline init: HikageView<VG> = {}, noinline performer: HikagePerformer<NLP> = {}): VG","description":"com.highcapable.hikage.core.layout.ViewGroup","location":"hikage-core/com.highcapable.hikage.core.layout/-view-group.html","searchKeys":["ViewGroup","inline fun <VG : ViewGroup, NLP : ViewGroup.LayoutParams> Hikage.Performer<*>.ViewGroup(noinline factory: ViewConstructor<VG>? = null, lparams: LayoutParams? = null, id: String? = null, noinline attrs: HikageAttribute = {}, noinline init: HikageView<VG> = {}, noinline performer: HikagePerformer<NLP> = {}): VG","com.highcapable.hikage.core.layout.ViewGroup"]},{"name":"inline fun <VG : ViewGroup> Hikage.Performer<*>.ViewGroup(noinline factory: ViewConstructor<VG>? = null, lparams: LayoutParams? = null, id: String? = null, noinline attrs: HikageAttribute = {}, noinline init: HikageView<VG> = {}, noinline performer: HikagePerformer<ViewGroup.LayoutParams> = {}): VG","description":"com.highcapable.hikage.core.layout.ViewGroup","location":"hikage-core/com.highcapable.hikage.core.layout/-view-group.html","searchKeys":["ViewGroup","inline fun <VG : ViewGroup> Hikage.Performer<*>.ViewGroup(noinline factory: ViewConstructor<VG>? = null, lparams: LayoutParams? = null, id: String? = null, noinline attrs: HikageAttribute = {}, noinline init: HikageView<VG> = {}, noinline performer: HikagePerformer<ViewGroup.LayoutParams> = {}): VG","com.highcapable.hikage.core.layout.ViewGroup"]},{"name":"inline fun Hikage.Attribute.android(block: AttributeScope.() -> Unit)","description":"com.highcapable.hikage.core.attribute.android","location":"hikage-core/com.highcapable.hikage.core.attribute/android.html","searchKeys":["android","inline fun Hikage.Attribute.android(block: AttributeScope.() -> Unit)","com.highcapable.hikage.core.attribute.android"]},{"name":"inline fun Hikage.Attribute.app(block: AttributeScope.() -> Unit)","description":"com.highcapable.hikage.core.attribute.app","location":"hikage-core/com.highcapable.hikage.core.attribute/app.html","searchKeys":["app","inline fun Hikage.Attribute.app(block: AttributeScope.() -> Unit)","com.highcapable.hikage.core.attribute.app"]},{"name":"inline fun Hikage.Attribute.namespace(name: String, block: AttributeScope.() -> Unit)","description":"com.highcapable.hikage.core.attribute.namespace","location":"hikage-core/com.highcapable.hikage.core.attribute/namespace.html","searchKeys":["namespace","inline fun Hikage.Attribute.namespace(name: String, block: AttributeScope.() -> Unit)","com.highcapable.hikage.core.attribute.namespace"]},{"name":"inline fun HikageAttribute.isEmpty(): Boolean","description":"com.highcapable.hikage.core.attribute.isEmpty","location":"hikage-core/com.highcapable.hikage.core.attribute/is-empty.html","searchKeys":["isEmpty","inline fun HikageAttribute.isEmpty(): Boolean","com.highcapable.hikage.core.attribute.isEmpty"]},{"name":"interface Attribute","description":"com.highcapable.hikage.core.Hikage.Attribute","location":"hikage-core/com.highcapable.hikage.core/-hikage/-attribute/index.html","searchKeys":["Attribute","interface Attribute","com.highcapable.hikage.core.Hikage.Attribute"]},{"name":"interface AttributeScope","description":"com.highcapable.hikage.core.attribute.AttributeScope","location":"hikage-core/com.highcapable.hikage.core.attribute/-attribute-scope/index.html","searchKeys":["AttributeScope","interface AttributeScope","com.highcapable.hikage.core.attribute.AttributeScope"]},{"name":"interface HikageBuilder","description":"com.highcapable.hikage.core.builder.HikageBuilder","location":"hikage-core/com.highcapable.hikage.core.builder/-hikage-builder/index.html","searchKeys":["HikageBuilder","interface HikageBuilder","com.highcapable.hikage.core.builder.HikageBuilder"]},{"name":"interface Performer<LP : ViewGroup.LayoutParams> : DisplayDensity, ResourcesScope","description":"com.highcapable.hikage.core.Hikage.Performer","location":"hikage-core/com.highcapable.hikage.core/-hikage/-performer/index.html","searchKeys":["Performer","interface Performer<LP : ViewGroup.LayoutParams> : DisplayDensity, ResourcesScope","com.highcapable.hikage.core.Hikage.Performer"]},{"name":"interface ResourcesScope","description":"com.highcapable.hikage.core.layout.extension.ResourcesScope","location":"hikage-core/com.highcapable.hikage.core.layout.extension/-resources-scope/index.html","searchKeys":["ResourcesScope","interface ResourcesScope","com.highcapable.hikage.core.layout.extension.ResourcesScope"]},{"name":"object Companion","description":"com.highcapable.hikage.core.Hikage.Companion","location":"hikage-core/com.highcapable.hikage.core/-hikage/-companion/index.html","searchKeys":["Companion","object Companion","com.highcapable.hikage.core.Hikage.Companion"]},{"name":"object Companion","description":"com.highcapable.hikage.core.base.HikageFactory.Config.Companion","location":"hikage-core/com.highcapable.hikage.core.base/-hikage-factory/-config/-companion/index.html","searchKeys":["Companion","object Companion","com.highcapable.hikage.core.base.HikageFactory.Config.Companion"]},{"name":"operator fun get(id: String): View","description":"com.highcapable.hikage.core.Hikage.get","location":"hikage-core/com.highcapable.hikage.core/-hikage/get.html","searchKeys":["get","operator fun get(id: String): View","com.highcapable.hikage.core.Hikage.get"]},{"name":"typealias HikageAttribute = Hikage.Attribute.() -> Unit","description":"com.highcapable.hikage.core.attribute.HikageAttribute","location":"hikage-core/com.highcapable.hikage.core.attribute/-hikage-attribute/index.html","searchKeys":["HikageAttribute","typealias HikageAttribute = Hikage.Attribute.() -> Unit","com.highcapable.hikage.core.attribute.HikageAttribute"]},{"name":"typealias HikagePerformer<LP> = Hikage.Performer<LP>.() -> Unit","description":"com.highcapable.hikage.core.base.HikagePerformer","location":"hikage-core/com.highcapable.hikage.core.base/-hikage-performer/index.html","searchKeys":["HikagePerformer","typealias HikagePerformer<LP> = Hikage.Performer<LP>.() -> Unit","com.highcapable.hikage.core.base.HikagePerformer"]},{"name":"typealias HikageView<V> = V.() -> Unit","description":"com.highcapable.hikage.core.base.HikageView","location":"hikage-core/com.highcapable.hikage.core.base/-hikage-view/index.html","searchKeys":["HikageView","typealias HikageView<V> = V.() -> Unit","com.highcapable.hikage.core.base.HikageView"]},{"name":"typealias ViewConstructor<V> = (Context, AttributeSet?) -> V","description":"com.highcapable.hikage.core.base.ViewConstructor","location":"hikage-core/com.highcapable.hikage.core.base/-view-constructor/index.html","searchKeys":["ViewConstructor","typealias ViewConstructor<V> = (Context, AttributeSet?) -> V","com.highcapable.hikage.core.base.ViewConstructor"]},{"name":"val Hikage.Attribute.android: AttributeScope","description":"com.highcapable.hikage.core.attribute.android","location":"hikage-core/com.highcapable.hikage.core.attribute/android.html","searchKeys":["android","val Hikage.Attribute.android: AttributeScope","com.highcapable.hikage.core.attribute.android"]},{"name":"val Hikage.Attribute.app: AttributeScope","description":"com.highcapable.hikage.core.attribute.app","location":"hikage-core/com.highcapable.hikage.core.attribute/app.html","searchKeys":["app","val Hikage.Attribute.app: AttributeScope","com.highcapable.hikage.core.attribute.app"]},{"name":"val alias: String","description":"com.highcapable.hikage.annotation.HikageView.alias","location":"hikage-core/com.highcapable.hikage.annotation/-hikage-view/alias.html","searchKeys":["alias","val alias: String","com.highcapable.hikage.annotation.HikageView.alias"]},{"name":"val alias: String","description":"com.highcapable.hikage.annotation.HikageViewDeclaration.alias","location":"hikage-core/com.highcapable.hikage.annotation/-hikage-view-declaration/alias.html","searchKeys":["alias","val alias: String","com.highcapable.hikage.annotation.HikageViewDeclaration.alias"]},{"name":"val attrs: AttributeSet","description":"com.highcapable.hikage.core.base.HikageFactory.Params.attrs","location":"hikage-core/com.highcapable.hikage.core.base/-hikage-factory/-params/attrs.html","searchKeys":["attrs","val attrs: AttributeSet","com.highcapable.hikage.core.base.HikageFactory.Params.attrs"]},{"name":"val attrs: Boolean = true","description":"com.highcapable.hikage.annotation.HikageView.attrs","location":"hikage-core/com.highcapable.hikage.annotation/-hikage-view/attrs.html","searchKeys":["attrs","val attrs: Boolean = true","com.highcapable.hikage.annotation.HikageView.attrs"]},{"name":"val attrs: Boolean = true","description":"com.highcapable.hikage.annotation.HikageViewDeclaration.attrs","location":"hikage-core/com.highcapable.hikage.annotation/-hikage-view-declaration/attrs.html","searchKeys":["attrs","val attrs: Boolean = true","com.highcapable.hikage.annotation.HikageViewDeclaration.attrs"]},{"name":"val factory: ViewConstructor<View>?","description":"com.highcapable.hikage.core.base.HikageFactory.Params.factory","location":"hikage-core/com.highcapable.hikage.core.base/-hikage-factory/-params/factory.html","searchKeys":["factory","val factory: ViewConstructor<View>?","com.highcapable.hikage.core.base.HikageFactory.Params.factory"]},{"name":"val id: String?","description":"com.highcapable.hikage.core.base.HikageFactory.Params.id","location":"hikage-core/com.highcapable.hikage.core.base/-hikage-factory/-params/id.html","searchKeys":["id","val id: String?","com.highcapable.hikage.core.base.HikageFactory.Params.id"]},{"name":"val init: Boolean = true","description":"com.highcapable.hikage.annotation.HikageView.init","location":"hikage-core/com.highcapable.hikage.annotation/-hikage-view/init.html","searchKeys":["init","val init: Boolean = true","com.highcapable.hikage.annotation.HikageView.init"]},{"name":"val init: Boolean = true","description":"com.highcapable.hikage.annotation.HikageViewDeclaration.init","location":"hikage-core/com.highcapable.hikage.annotation/-hikage-view-declaration/init.html","searchKeys":["init","val init: Boolean = true","com.highcapable.hikage.annotation.HikageViewDeclaration.init"]},{"name":"val lparams: KClass<*>","description":"com.highcapable.hikage.annotation.HikageView.lparams","location":"hikage-core/com.highcapable.hikage.annotation/-hikage-view/lparams.html","searchKeys":["lparams","val lparams: KClass<*>","com.highcapable.hikage.annotation.HikageView.lparams"]},{"name":"val lparams: KClass<*>","description":"com.highcapable.hikage.annotation.HikageViewDeclaration.lparams","location":"hikage-core/com.highcapable.hikage.annotation/-hikage-view-declaration/lparams.html","searchKeys":["lparams","val lparams: KClass<*>","com.highcapable.hikage.annotation.HikageViewDeclaration.lparams"]},{"name":"val performer: Boolean = true","description":"com.highcapable.hikage.annotation.HikageView.performer","location":"hikage-core/com.highcapable.hikage.annotation/-hikage-view/performer.html","searchKeys":["performer","val performer: Boolean = true","com.highcapable.hikage.annotation.HikageView.performer"]},{"name":"val performer: Boolean = true","description":"com.highcapable.hikage.annotation.HikageViewDeclaration.performer","location":"hikage-core/com.highcapable.hikage.annotation/-hikage-view-declaration/performer.html","searchKeys":["performer","val performer: Boolean = true","com.highcapable.hikage.annotation.HikageViewDeclaration.performer"]},{"name":"val privateFactory: Boolean","description":"com.highcapable.hikage.core.base.HikageFactory.Config.privateFactory","location":"hikage-core/com.highcapable.hikage.core.base/-hikage-factory/-config/private-factory.html","searchKeys":["privateFactory","val privateFactory: Boolean","com.highcapable.hikage.core.base.HikageFactory.Config.privateFactory"]},{"name":"val privateFactoryViews: List<String>","description":"com.highcapable.hikage.core.base.HikageFactory.Config.privateFactoryViews","location":"hikage-core/com.highcapable.hikage.core.base/-hikage-factory/-config/private-factory-views.html","searchKeys":["privateFactoryViews","val privateFactoryViews: List<String>","com.highcapable.hikage.core.base.HikageFactory.Config.privateFactoryViews"]},{"name":"val root: View","description":"com.highcapable.hikage.core.Hikage.root","location":"hikage-core/com.highcapable.hikage.core/-hikage/root.html","searchKeys":["root","val root: View","com.highcapable.hikage.core.Hikage.root"]},{"name":"val view: KClass<*>","description":"com.highcapable.hikage.annotation.HikageViewDeclaration.view","location":"hikage-core/com.highcapable.hikage.annotation/-hikage-view-declaration/view.html","searchKeys":["view","val view: KClass<*>","com.highcapable.hikage.annotation.HikageViewDeclaration.view"]},{"name":"val viewClass: KClass<out View>","description":"com.highcapable.hikage.core.base.HikageFactory.Params.viewClass","location":"hikage-core/com.highcapable.hikage.core.base/-hikage-factory/-params/view-class.html","searchKeys":["viewClass","val viewClass: KClass<out View>","com.highcapable.hikage.core.base.HikageFactory.Params.viewClass"]},{"name":"var defaultPrivateFactoryViews: List<String>","description":"com.highcapable.hikage.core.base.HikageFactory.Config.Companion.defaultPrivateFactoryViews","location":"hikage-core/com.highcapable.hikage.core.base/-hikage-factory/-config/-companion/default-private-factory-views.html","searchKeys":["defaultPrivateFactoryViews","var defaultPrivateFactoryViews: List<String>","com.highcapable.hikage.core.base.HikageFactory.Config.Companion.defaultPrivateFactoryViews"]},{"name":"var defaultProcessPrivateFactory: Boolean","description":"com.highcapable.hikage.core.base.HikageFactory.Config.Companion.defaultProcessPrivateFactory","location":"hikage-core/com.highcapable.hikage.core.base/-hikage-factory/-config/-companion/default-process-private-factory.html","searchKeys":["defaultProcessPrivateFactory","var defaultProcessPrivateFactory: Boolean","com.highcapable.hikage.core.base.HikageFactory.Config.Companion.defaultProcessPrivateFactory"]},{"name":"var isAutoProcessWithFactory2: Boolean","description":"com.highcapable.hikage.core.Hikage.Companion.isAutoProcessWithFactory2","location":"hikage-core/com.highcapable.hikage.core/-hikage/-companion/is-auto-process-with-factory2.html","searchKeys":["isAutoProcessWithFactory2","var isAutoProcessWithFactory2: Boolean","com.highcapable.hikage.core.Hikage.Companion.isAutoProcessWithFactory2"]}]